{
  "methods": {
    "GetScaleFlag": {
      "memberof": "ApiPictureForm",
      "name": "GetScaleFlag",
      "description": "<p>Returns the current scaling condition of the picture form.</p>",
      "tags": {
        "typeofeditors": [
          "CDE"
        ]
      },
      "returns": [
        [
          "ScaleFlag"
        ]
      ],
      "see": null,
      "inherits": null
    },
    "SetScaleFlag": {
      "memberof": "ApiPictureForm",
      "name": "SetScaleFlag",
      "description": "<p>Sets the condition for scaling to the current picture form.</p>",
      "tags": {
        "typeofeditors": [
          "CDE"
        ]
      },
      "returns": [
        [
          "boolean"
        ]
      ],
      "see": null,
      "inherits": null,
      "params": [
        {
          "type": "ScaleFlag",
          "name": "sScaleFlag",
          "description": "<p>Picture scaling condition: &quot;always&quot;, &quot;never&quot;, &quot;tooBig&quot; or &quot;tooSmall&quot;</p>",
          "optional": false
        }
      ]
    },
    "SetLockAspectRatio": {
      "memberof": "ApiPictureForm",
      "name": "SetLockAspectRatio",
      "description": "<p>Sets the lock aspect ratio to the current picture form</p>",
      "tags": {
        "typeofeditors": [
          "CDE"
        ]
      },
      "returns": [
        [
          "boolean"
        ]
      ],
      "see": null,
      "inherits": null,
      "params": [
        {
          "type": "boolean",
          "name": "isLock",
          "optional": true,
          "defaultValue": true
        }
      ]
    },
    "IsLockAspectRatio": {
      "memberof": "ApiPictureForm",
      "name": "IsLockAspectRatio",
      "description": "<p>Gets the lock aspect ratio to the current picture form</p>",
      "tags": {
        "typeofeditors": [
          "CDE"
        ]
      },
      "returns": [
        [
          "boolean"
        ]
      ],
      "see": null,
      "inherits": null
    },
    "SetPicturePosition": {
      "memberof": "ApiPictureForm",
      "name": "SetPicturePosition",
      "description": "<p>Sets the position of the picture inside the form</p>",
      "tags": {
        "typeofeditors": [
          "CDE"
        ]
      },
      "returns": [
        [
          "boolean"
        ]
      ],
      "see": null,
      "inherits": null,
      "params": [
        {
          "type": "percentage",
          "name": "nShiftX",
          "description": "<p>horizontal position measured in percent</p>",
          "optional": false
        },
        {
          "type": "percentage",
          "name": "nShiftY",
          "description": "<p>vertical position measured in percent</p>",
          "optional": false
        }
      ]
    },
    "GetPicturePosition": {
      "memberof": "ApiPictureForm",
      "name": "GetPicturePosition",
      "description": "<p>Gets the position of the picture inside the form</p>",
      "tags": {
        "typeofeditors": [
          "CDE"
        ]
      },
      "returns": [
        [
          "Array.<percentage>"
        ]
      ],
      "see": null,
      "inherits": null
    },
    "SetRespectBorders": {
      "memberof": "ApiPictureForm",
      "name": "SetRespectBorders",
      "description": "<p>Take into account border width</p>",
      "tags": {
        "typeofeditors": [
          "CDE"
        ]
      },
      "returns": [
        [
          "boolean"
        ]
      ],
      "see": null,
      "inherits": null,
      "params": [
        {
          "type": "boolean",
          "name": "isRespect",
          "optional": true,
          "defaultValue": true
        }
      ]
    },
    "IsRespectBorders": {
      "memberof": "ApiPictureForm",
      "name": "IsRespectBorders",
      "description": "<p>Whether to take into account the width of the border</p>",
      "tags": {
        "typeofeditors": [
          "CDE"
        ]
      },
      "returns": [
        [
          "boolean"
        ]
      ],
      "see": null,
      "inherits": null
    },
    "GetImage": {
      "memberof": "ApiPictureForm",
      "name": "GetImage",
      "description": "<p>Returns an image in the base64 format from the current picture form.</p>",
      "tags": {
        "typeofeditors": [
          "CDE"
        ]
      },
      "returns": [
        [
          "base64img"
        ]
      ],
      "see": null,
      "inherits": null
    },
    "SetImage": {
      "memberof": "ApiPictureForm",
      "name": "SetImage",
      "description": "<p>Sets an image to the current picture form.</p>",
      "tags": {
        "typeofeditors": [
          "CDE"
        ]
      },
      "returns": [
        [
          "boolean"
        ]
      ],
      "see": null,
      "inherits": null,
      "params": [
        {
          "type": "string",
          "name": "sImageSrc",
          "description": "<p>The image source where the image to be inserted should be taken from (currently, only internet URL or base64 encoded images are supported).</p>",
          "optional": false
        }
      ]
    },
    "GetClassType": {
      "memberof": "ApiPictureForm",
      "name": "GetClassType",
      "description": "<p>Returns a type of the ApiFormBase class.</p>",
      "tags": {
        "typeofeditors": [
          "CDE"
        ]
      },
      "returns": [
        [
          "\"form\""
        ]
      ],
      "see": null,
      "inherits": "Inherited From: {@link ApiFormBase#GetClassType}"
    },
    "GetFormType": {
      "memberof": "ApiPictureForm",
      "name": "GetFormType",
      "description": "<p>Returns a type of the current form.</p>",
      "tags": {
        "typeofeditors": [
          "CDE"
        ]
      },
      "returns": [
        [
          "FormType"
        ]
      ],
      "see": null,
      "inherits": "Inherited From: {@link ApiFormBase#GetFormType}"
    },
    "GetFormKey": {
      "memberof": "ApiPictureForm",
      "name": "GetFormKey",
      "description": "<p>Returns the current form key.</p>",
      "tags": {
        "typeofeditors": [
          "CDE"
        ]
      },
      "returns": [
        [
          "string"
        ]
      ],
      "see": null,
      "inherits": "Inherited From: {@link ApiFormBase#GetFormKey}"
    },
    "SetFormKey": {
      "memberof": "ApiPictureForm",
      "name": "SetFormKey",
      "description": "<p>Sets a key to the current form.</p>",
      "tags": {
        "typeofeditors": [
          "CDE"
        ]
      },
      "returns": [
        [
          "boolean"
        ]
      ],
      "see": null,
      "inherits": "Inherited From: {@link ApiFormBase#SetFormKey}",
      "params": [
        {
          "type": "string",
          "name": "sKey",
          "description": "<p>Form key.</p>",
          "optional": false
        }
      ]
    },
    "GetTipText": {
      "memberof": "ApiPictureForm",
      "name": "GetTipText",
      "description": "<p>Returns the tip text of the current form.</p>",
      "tags": {
        "typeofeditors": [
          "CDE"
        ]
      },
      "returns": [
        [
          "string"
        ]
      ],
      "see": null,
      "inherits": "Inherited From: {@link ApiFormBase#GetTipText}"
    },
    "SetTipText": {
      "memberof": "ApiPictureForm",
      "name": "SetTipText",
      "description": "<p>Sets the tip text to the current form.</p>",
      "tags": {
        "typeofeditors": [
          "CDE"
        ]
      },
      "returns": [
        [
          "boolean"
        ]
      ],
      "see": null,
      "inherits": "Inherited From: {@link ApiFormBase#SetTipText}",
      "params": [
        {
          "type": "string",
          "name": "sText",
          "description": "<p>Tip text.</p>",
          "optional": false
        }
      ]
    },
    "IsRequired": {
      "memberof": "ApiPictureForm",
      "name": "IsRequired",
      "description": "<p>Checks if the current form is required.</p>",
      "tags": {
        "typeofeditors": [
          "CDE"
        ]
      },
      "returns": [
        [
          "boolean"
        ]
      ],
      "see": null,
      "inherits": "Inherited From: {@link ApiFormBase#IsRequired}"
    },
    "SetRequired": {
      "memberof": "ApiPictureForm",
      "name": "SetRequired",
      "description": "<p>Specifies if the current form should be required.</p>",
      "tags": {
        "typeofeditors": [
          "CDE"
        ]
      },
      "returns": [
        [
          "boolean"
        ]
      ],
      "see": null,
      "inherits": "Inherited From: {@link ApiFormBase#SetRequired}",
      "params": [
        {
          "type": "boolean",
          "name": "bRequired",
          "description": "<p>Defines if the current form is required (true) or not (false).</p>",
          "optional": false
        }
      ]
    },
    "IsFixed": {
      "memberof": "ApiPictureForm",
      "name": "IsFixed",
      "description": "<p>Checks if the current form is fixed-size</p>",
      "tags": {
        "typeofeditors": [
          "CDE"
        ]
      },
      "returns": [
        [
          "boolean"
        ]
      ],
      "see": null,
      "inherits": "Inherited From: {@link ApiFormBase#IsFixed}"
    },
    "ToFixed": {
      "memberof": "ApiPictureForm",
      "name": "ToFixed",
      "description": "<p>Convert form to a fixed-size mode</p>",
      "tags": {
        "typeofeditors": [
          "CDE"
        ]
      },
      "returns": [
        [
          "boolean"
        ]
      ],
      "see": null,
      "inherits": "Inherited From: {@link ApiFormBase#ToFixed}",
      "params": [
        {
          "type": "twips",
          "name": "nWidth",
          "description": "<p>The wrapper shape width measured in twentieths of a point (1/1440 of an inch).</p>",
          "optional": false
        },
        {
          "type": "twips",
          "name": "nHeight",
          "description": "<p>The wrapper shape height measured in twentieths of a point (1/1440 of an inch).</p>",
          "optional": false
        }
      ]
    },
    "ToInline": {
      "memberof": "ApiPictureForm",
      "name": "ToInline",
      "description": "<p>Convert form to an inline mode\n<em>Picture form can't be converted to inline mode, it's always a fixed-size object</em></p>",
      "tags": {
        "typeofeditors": [
          "CDE"
        ]
      },
      "returns": [
        [
          "boolean"
        ]
      ],
      "see": null,
      "inherits": "Inherited From: {@link ApiFormBase#ToInline}"
    },
    "SetBorderColor": {
      "memberof": "ApiPictureForm",
      "name": "SetBorderColor",
      "description": "<p>Sets the border color to the current form.</p>",
      "tags": {
        "typeofeditors": [
          "CDE"
        ]
      },
      "returns": [
        [
          "boolean"
        ]
      ],
      "see": null,
      "inherits": "Inherited From: {@link ApiFormBase#SetBorderColor}",
      "params": [
        {
          "type": "byte",
          "name": "r",
          "description": "<p>Red color component value.</p>",
          "optional": false
        },
        {
          "type": "byte",
          "name": "g",
          "description": "<p>Green color component value.</p>",
          "optional": false
        },
        {
          "type": "byte",
          "name": "b",
          "description": "<p>Blue color component value.</p>",
          "optional": false
        },
        {
          "type": "boolean",
          "name": "bNone",
          "description": "<p>Defines that border color will not be set.</p>",
          "optional": false
        }
      ]
    },
    "SetBackgroundColor": {
      "memberof": "ApiPictureForm",
      "name": "SetBackgroundColor",
      "description": "<p>Sets the background color to the current form.</p>",
      "tags": {
        "typeofeditors": [
          "CDE"
        ]
      },
      "returns": [
        [
          "boolean"
        ]
      ],
      "see": null,
      "inherits": "Inherited From: {@link ApiFormBase#SetBackgroundColor}",
      "params": [
        {
          "type": "byte",
          "name": "r",
          "description": "<p>Red color component value.</p>",
          "optional": false
        },
        {
          "type": "byte",
          "name": "g",
          "description": "<p>Green color component value.</p>",
          "optional": false
        },
        {
          "type": "byte",
          "name": "b",
          "description": "<p>Blue color component value.</p>",
          "optional": false
        },
        {
          "type": "boolean",
          "name": "bNone",
          "description": "<p>Defines that background color will not be set.</p>",
          "optional": false
        }
      ]
    },
    "GetText": {
      "memberof": "ApiPictureForm",
      "name": "GetText",
      "description": "<p>Returns the text from the current form.</p>",
      "tags": {
        "typeofeditors": [
          "CDE"
        ]
      },
      "returns": [
        [
          "string"
        ]
      ],
      "see": null,
      "inherits": "Inherited From: {@link ApiFormBase#GetText}"
    },
    "Clear": {
      "memberof": "ApiPictureForm",
      "name": "Clear",
      "description": "<p>Clears the current form.</p>",
      "tags": {
        "typeofeditors": [
          "CDE"
        ]
      },
      "returns": [],
      "see": null,
      "inherits": "Inherited From: {@link ApiFormBase#Clear}"
    },
    "GetWrapperShape": {
      "memberof": "ApiPictureForm",
      "name": "GetWrapperShape",
      "description": "<p>Gets the shape in which the form placed.</p>",
      "tags": {
        "typeofeditors": [
          "CDE"
        ]
      },
      "returns": [
        [
          "ApiShape"
        ]
      ],
      "see": null,
      "inherits": "Inherited From: {@link ApiFormBase#GetWrapperShape}"
    },
    "SetPlaceholderText": {
      "memberof": "ApiPictureForm",
      "name": "SetPlaceholderText",
      "description": "<p>Sets the placeholder text to the current form.\n<em>Can't be set to checkbox or radio button</em></p>",
      "tags": {
        "typeofeditors": [
          "CDE"
        ]
      },
      "returns": [
        [
          "boolean"
        ]
      ],
      "see": null,
      "inherits": "Inherited From: {@link ApiFormBase#SetPlaceholderText}",
      "params": [
        {
          "type": "string",
          "name": "sText",
          "description": "<p>The text that will be set to the current form.</p>",
          "optional": false
        }
      ]
    },
    "SetTextPr": {
      "memberof": "ApiPictureForm",
      "name": "SetTextPr",
      "description": "<p>Sets the text properties to the current form.</p>",
      "tags": {
        "typeofeditors": [
          "CDE"
        ]
      },
      "returns": [
        [
          "boolean"
        ]
      ],
      "see": null,
      "inherits": "Inherited From: {@link ApiFormBase#SetTextPr}",
      "params": [
        {
          "type": "ApiTextPr",
          "name": "oTextPr",
          "description": "<p>The text properties that will be set to the current form.</p>",
          "optional": false
        }
      ]
    },
    "GetTextPr": {
      "memberof": "ApiPictureForm",
      "name": "GetTextPr",
      "description": "<p>Gets the text properties from the current form.</p>",
      "tags": {
        "typeofeditors": [
          "CDE"
        ]
      },
      "returns": [
        [
          "ApiTextPr"
        ]
      ],
      "see": null,
      "inherits": "Inherited From: {@link ApiFormBase#GetTextPr}"
    }
  },
  "comment": "/**\n\t * Class representing a document picture form.\n\t * @constructor\n\t * @extends {ApiFormBase}\n\t */",
  "description": "<p>Class representing a document picture form.</p>",
  "scope": "global",
  "params": []
}