{
  "methods": {
    "GetText": {
      "memberof": "ApiComment",
      "name": "GetText",
      "description": "<p>Returns the text of comment.</p>",
      "tags": {
        "typeofeditors": [
          "CSE"
        ]
      },
      "returns": [
        [
          "string"
        ]
      ],
      "see": null,
      "inherits": null
    },
    "Delete": {
      "memberof": "ApiComment",
      "name": "Delete",
      "description": "<p>Deletes the object.</p>",
      "tags": {
        "typeofeditors": [
          "CSE"
        ]
      },
      "returns": [],
      "see": null,
      "inherits": null
    }
  },
  "comment": "/**\r\n\t * Class representing a comment.\r\n\t * @constructor\r\n\t * @property {string} Text - Returns the text from the first cell in range.\r\n\t */",
  "description": "<p>Class representing a comment.</p>",
  "scope": "global",
  "params": [],
  "properties": [
    {
      "type": "string",
      "name": "Text",
      "description": "<p>Returns the text from the first cell in range.</p>"
    }
  ]
}